[
  {
    "id": "main",
    "components": [
      "section"
    ]
  },
  {
    "id": "section",
    "components": [
      "text",
      "image",
      "button",
      "title",
      "hero",
      "cards",
      "columns",
      "fragment",
      "carousel-heading"
    ]
  },
  {
    "id": "cards",
    "components": [
      "card"
    ]
  },
  {
    "id": "carousel-card",
    "components": [
      "carousel-card-item"
    ]
  },
  {
    "id": "carousel-heading",
    "components": [
      "banner-carousel-item"
    ]
  },
  {
    "id": "columns",
    "components": [
      "column"
    ]
  },
  {
    "id": "column",
    "components": [
      "text",
      "image",
      "button",
      "title"
    ]
  }
]